{
    "data": [{
        "id": 1,
        "projectImg": "img.png",
        "title": "leonidasesteban.com",
        "description": "Accede a m谩s de 120 proyectos que te ayudar谩n a mejorar tus habilidades como desarrollador Front-End.",
        "buttonFirst": "VER C贸DIGO",
        "buttonSecond": "VER PROYECTO",
        "profileImg": "leonidas.png",
        "comment": "\"Jaume ha sido de gran ayuda para acelerar ciertos esfuerzos de desarrollo. Lo que nos hubiera llevado 6 meses solo les llev贸 1,5 meses\".",
        "client": "'EONIDAS ESTEBAN / COFUNDADOR Y CEO LEONIDASESTEBAN.COM",
        "imageFirst": false,
        "imgSize": "90%"
    },{
        "id": 2,
        "projectImg": " iPad.png",
        "title": "MARVOL",
        "description": "Es el sitio oficial de Marvol Entertainment. Explore pel铆culas, personajes, c贸mics, programas de televisi贸n, videos y m谩s oficiales de Marvol.",
        "buttonFirst": "VER C贸DIGO",
        "buttonSecond": "VER PROYECTO",
        "profileImg": "jason.png",
        "comment": "\"Jaume ha superado mis expectativas desde el dise帽o hasta el desarrollo\".",
        "client": "JASON LOPEZ / COFUNDADOR Y CEO MARVOL",
        "imageFirst": true,
        "imgSize": "90%"
    },{
        "id": 3,
        "projectImg": " Iphone X.png",
        "title": "NETNET",
        "description": "Pel铆culas y series ilimitadas y mucho m谩s. Disfruta donde quieras. Cancela cuando quieras.",
        "buttonFirst": "VER C贸DIGO",
        "buttonSecond": "VER PROYECTO",
        "profileImg": "/marco.png",
        "comment": "\"Por primera vez en la historia de nuestra empresa, aparecimos en todas las plataformas en las que trabajamos\".",
        "client": "MARCO CORTEZ / NETNET",
        "imageFirst": false,
        "imgSize": "60%"
    }]
}
